{"name": "03a5976c-6d4c6239-0000029.jpg", "video_name": "03a5976c-6d4c6239", "index": 28, "labels": [{"id": "00010722", "category": "car", "attributes": {"Crowd": false, "Occluded": true, "Truncated": false}, "box2d": {"x1": 21.626754748142023, "x2": 37.233691164327, "y1": 40.87530966143684, "y2": 44.145334434351774}}, {"id": "00010732", "category": "trailer", "attributes": {"Crowd": false, "Occluded": true, "Truncated": false}, "box2d": {"x1": 71.56895127993393, "x2": 91.33773740710157, "y1": 40.132122213047055, "y2": 48.15854665565648}}, {"id": "00010723", "category": "car", "attributes": {"Crowd": false, "Occluded": true, "Truncated": false}, "box2d": {"x1": 48.827415359207265, "x2": 53.732452518579684, "y1": 42.80759702725021, "y2": 48.15854665565649}}, {"id": "00010724", "category": "car", "attributes": {"Crowd": false, "Occluded": false, "Truncated": true}, "box2d": {"x1": 0.0, "x2": 43.179190751445084, "y1": 43.10487200660611, "y2": 69.11643270024773}}, {"id": "00010729", "category": "car", "attributes": {"Crowd": false, "Occluded": false, "Truncated": false}, "box2d": {"x1": 52.24607762180014, "x2": 62.65070189925681, "y1": 42.06440957886044, "y2": 50.23947151114781}}, {"id": "00010730", "category": "car", "attributes": {"Crowd": false, "Occluded": true, "Truncated": false}, "box2d": {"x1": 68.5962014863749, "x2": 79.4467382328654, "y1": 41.76713459950455, "y2": 50.68538398018167}}, {"id": "00010733", "category": "pedestrian", "attributes": {"Crowd": false, "Occluded": true, "Truncated": false}, "box2d": {"x1": 41.69281585466556, "x2": 44.96284062758051, "y1": 42.95623451692815, "y2": 50.09083402146986}}, {"id": "00010734", "category": "car", "attributes": {"Crowd": false, "Occluded": true, "Truncated": false}, "box2d": {"x1": 37.233691164327, "x2": 39.46325350949628, "y1": 43.25350949628406, "y2": 46.820809248554916}}]}