{"name": "03b997fa-922d0c49-0000071.jpg", "video_name": "03b997fa-922d0c49", "index": 70, "labels": [{"id": "00097024", "category": "car", "attributes": {"Crowd": false, "Occluded": true, "Truncated": false}, "box2d": {"x1": 15.235935430919465, "x2": 34.8490456817716, "y1": 46.88627643658643, "y2": 53.620391544175135}}, {"id": "00097025", "category": "car", "attributes": {"Crowd": false, "Occluded": false, "Truncated": false}, "box2d": {"x1": 78.35598312152905, "x2": 98.52852166790738, "y1": 43.98218929643879, "y2": 60.42659089386563}}, {"id": "00097032", "category": "motorcycle", "attributes": {"Crowd": false, "Occluded": false, "Truncated": false}, "box2d": {"x1": 144.86344243006, "x2": 153.17165694404756, "y1": 43.352970416073475, "y2": 55.28498062233223}}, {"id": "00097054", "category": "car", "attributes": {"Crowd": false, "Occluded": false, "Truncated": false}, "box2d": {"x1": 43.81294964028777, "x2": 55.46762589928057, "y1": 46.94244604316546, "y2": 53.7410071942446}}, {"id": "00097066", "category": "motorcycle", "attributes": {"Crowd": false, "Occluded": true, "Truncated": false}, "box2d": {"x1": 68.5251798561151, "x2": 71.33093525179855, "y1": 47.482014388489205, "y2": 51.36690647482014}}, {"id": "00097067", "category": "rider", "attributes": {"Crowd": false, "Occluded": true, "Truncated": false}, "box2d": {"x1": 68.3093525179856, "x2": 71.6546762589928, "y1": 46.07913669064748, "y2": 49.856115107913666}}, {"id": "00097033", "category": "car", "attributes": {"Crowd": false, "Occluded": true, "Truncated": false}, "box2d": {"x1": 109.22752914997412, "x2": 116.67938492637619, "y1": 45.28648209431509, "y2": 50.454704648916525}}, {"id": "00097034", "category": "car", "attributes": {"Crowd": false, "Occluded": true, "Truncated": false}, "box2d": {"x1": 107.30446959477358, "x2": 111.75154481617481, "y1": 44.92590842771499, "y2": 47.570115316115725}}, {"id": "00097042", "category": "car", "attributes": {"Crowd": false, "Occluded": false, "Truncated": false}, "box2d": {"x1": 102.13624704017214, "x2": 110.42944137197445, "y1": 45.76724698311522, "y2": 51.53642564871683}}, {"id": "00097052", "category": "car", "attributes": {"Crowd": false, "Occluded": true, "Truncated": false}, "box2d": {"x1": 100.2131874849716, "x2": 106.58332226157337, "y1": 45.28648209431509, "y2": 50.935469537716656}}, {"id": "00097035", "category": "pedestrian", "attributes": {"Crowd": false, "Occluded": true, "Truncated": false}, "box2d": {"x1": 129.7802281461798, "x2": 134.4992567878482, "y1": 43.53627433517157, "y2": 50.33451342671649}}, {"id": "00097056", "category": "car", "attributes": {"Crowd": false, "Occluded": true, "Truncated": false}, "box2d": {"x1": 96.84783326337067, "x2": 100.33337870717163, "y1": 46.36820309411539, "y2": 49.252792426916194}}, {"id": "00097038", "category": "car", "attributes": {"Crowd": false, "Occluded": true, "Truncated": false}, "box2d": {"x1": 30.742661053352297, "x2": 40.1175763849549, "y1": 46.72877676071549, "y2": 53.21910275951729}}, {"id": "00097051", "category": "car", "attributes": {"Crowd": false, "Occluded": true, "Truncated": false}, "box2d": {"x1": 34.75158968131568, "x2": 45.46036741093526, "y1": 46.650231603115216, "y2": 52.82619336252545}}, {"id": "00097063", "category": "car", "attributes": {"Crowd": false, "Occluded": true, "Truncated": false}, "box2d": {"x1": 44.57269152647996, "x2": 46.87687240162568, "y1": 47.330153998646615, "y2": 49.65322218337891}}, {"id": "00097069", "category": "car", "attributes": {"Crowd": false, "Occluded": true, "Truncated": false}, "box2d": {"x1": 54.63773496594168, "x2": 59.315208955645915, "y1": 47.05700125849, "y2": 50.84736811221584}}, {"id": "00097068", "category": "car", "attributes": {"Crowd": false, "Occluded": true, "Truncated": false}, "box2d": {"x1": 59.426617903585324, "x2": 60.65532708365754, "y1": 47.74412933033705, "y2": 50.815902280517584}}, {"id": "00097064", "category": "car", "attributes": {"Crowd": false, "Occluded": true, "Truncated": false}, "box2d": {"x1": 60.202316091624304, "x2": 62.05717646685184, "y1": 47.339262619937664, "y2": 50.64575285403893}}, {"id": "00097061", "category": "car", "attributes": {"Crowd": false, "Occluded": true, "Truncated": false}, "box2d": {"x1": 62.02114738299641, "x2": 64.43623651333934, "y1": 47.460231774843805, "y2": 50.686075905674315}}, {"id": "00097071", "category": "car", "attributes": {"Crowd": false, "Occluded": true, "Truncated": false}, "box2d": {"x1": 73.30730787312324, "x2": 74.83958383526772, "y1": 47.74249313629148, "y2": 50.00058402787283}}, {"id": "00097072", "category": "car", "attributes": {"Crowd": true, "Occluded": true, "Truncated": false}, "box2d": {"x1": 74.71861468036158, "x2": 76.49282895231835, "y1": 48.18604670428067, "y2": 49.798968769695925}}, {"id": "00097047", "category": "pedestrian", "attributes": {"Crowd": false, "Occluded": false, "Truncated": false}, "box2d": {"x1": 153.3224277093705, "x2": 157.53039032325597, "y1": 42.04918583349562, "y2": 51.3640456828039}}, {"id": "00097044", "category": "pedestrian", "attributes": {"Crowd": false, "Occluded": true, "Truncated": false}, "box2d": {"x1": 138.60421974173087, "x2": 143.72575100955302, "y1": 42.10019237169226, "y2": 51.34688681348126}}, {"id": "00097062", "category": "pedestrian", "attributes": {"Crowd": false, "Occluded": true, "Truncated": false}, "box2d": {"x1": 118.17061959601942, "x2": 120.02343681186935, "y1": 44.253035290903526, "y2": 46.39839963315909}}, {"id": "00097075", "category": "pedestrian", "attributes": {"Crowd": false, "Occluded": true, "Truncated": false}, "box2d": {"x1": 0.9701131891938557, "x2": 3.0832342194842433, "y1": 46.493466679805906, "y2": 51.55054914270918}}, {"id": "00097076", "category": "pedestrian", "attributes": {"Crowd": false, "Occluded": true, "Truncated": false}, "box2d": {"x1": 4.639259705425347, "x2": 6.858036713949191, "y1": 47.362727830902635, "y2": 51.58896989148341}}, {"id": "00097073", "category": "pedestrian", "attributes": {"Crowd": false, "Occluded": true, "Truncated": false}, "box2d": {"x1": 16.492647755039332, "x2": 18.13092666180228, "y1": 47.85248504847458, "y2": 49.76381043969802}}, {"id": "00097074", "category": "pedestrian", "attributes": {"Crowd": false, "Occluded": true, "Truncated": false}, "box2d": {"x1": 18.754358290126145, "x2": 20.25611395465885, "y1": 47.98197750348638, "y2": 49.34720992578883}}, {"id": "00097077", "category": "pedestrian", "attributes": {"Crowd": false, "Occluded": true, "Truncated": false}, "box2d": {"x1": 12.050651161331235, "x2": 15.600600160849329, "y1": 44.73894687954169, "y2": 51.15408417955943}}, {"id": "00097070", "category": "car", "attributes": {"Crowd": false, "Occluded": true, "Truncated": true}, "box2d": {"x1": 149.58960328317374, "x2": 160.0, "y1": 51.894664842681266, "y2": 81.68946648426812}}]}