{"name": "03935c73-98cac3ec-0000181.jpg", "video_name": "03935c73-98cac3ec", "index": 180, "labels": [{"id": "00108495", "category": "car", "attributes": {"Crowd": false, "Occluded": true, "Truncated": false}, "box2d": {"x1": 51.03448275862069, "x2": 102.06896551724138, "y1": 39.6551724137931, "y2": 70.6896551724138}}, {"id": "00108499", "category": "car", "attributes": {"Crowd": false, "Occluded": true, "Truncated": true}, "box2d": {"x1": 150.51724137931035, "x2": 160.0, "y1": 50.3448275862069, "y2": 59.6551724137931}}, {"id": "00108544", "category": "car", "attributes": {"Crowd": false, "Occluded": true, "Truncated": false}, "box2d": {"x1": 34.6551724137931, "x2": 55.17241379310345, "y1": 41.20689655172414, "y2": 50.17241379310345}}, {"id": "00108543", "category": "car", "attributes": {"Crowd": false, "Occluded": false, "Truncated": true}, "box2d": {"x1": 154.13793103448276, "x2": 160.0, "y1": 52.58620689655172, "y2": 61.55172413793104}}, {"id": "00108521", "category": "car", "attributes": {"Crowd": false, "Occluded": true, "Truncated": false}, "box2d": {"x1": 99.13793103448276, "x2": 106.89655172413794, "y1": 46.55172413793104, "y2": 52.758620689655174}}]}