{"name": "039f729b-e5d9aec8-0000170.jpg", "video_name": "039f729b-e5d9aec8", "index": 169, "labels": [{"id": "00017946", "category": "car", "attributes": {"Crowd": false, "Occluded": true, "Truncated": false}, "box2d": {"x1": 108.13901125795398, "x2": 118.3220753793441, "y1": 37.421928536466, "y2": 48.57415565345081}}, {"id": "00017956", "category": "car", "attributes": {"Crowd": false, "Occluded": true, "Truncated": false}, "box2d": {"x1": 101.78169358786099, "x2": 104.91434165442976, "y1": 37.79784630445423, "y2": 40.554576603034754}}, {"id": "00017958", "category": "car", "attributes": {"Crowd": false, "Occluded": false, "Truncated": false}, "box2d": {"x1": 98.36514929025942, "x2": 102.40822320117475, "y1": 37.67254038179149, "y2": 41.43171806167401}}, {"id": "00017959", "category": "car", "attributes": {"Crowd": false, "Occluded": false, "Truncated": false}, "box2d": {"x1": 89.96965247185511, "x2": 95.76700930004895, "y1": 37.547234459128724, "y2": 42.05824767498776}}, {"id": "00017960", "category": "car", "attributes": {"Crowd": false, "Occluded": true, "Truncated": false}, "box2d": {"x1": 80.0704845814978, "x2": 85.86784140969164, "y1": 37.54723445912874, "y2": 43.43661282427802}}, {"id": "00017961", "category": "car", "attributes": {"Crowd": false, "Occluded": false, "Truncated": false}, "box2d": {"x1": 67.16397454723445, "x2": 83.86294664708761, "y1": 37.92315222711698, "y2": 48.32354380812531}}, {"id": "00017963", "category": "car", "attributes": {"Crowd": false, "Occluded": false, "Truncated": true}, "box2d": {"x1": 38.46891825746451, "x2": 63.31277533039648, "y1": 36.16886930983847, "y2": 48.57415565345081}}, {"id": "00017964", "category": "car", "attributes": {"Crowd": false, "Occluded": false, "Truncated": true}, "box2d": {"x1": 0.0, "x2": 1.912873225648556, "y1": 52.45863925599608, "y2": 63.73617229564366}}, {"id": "00017957", "category": "bus", "attributes": {"Crowd": false, "Occluded": true, "Truncated": false}, "box2d": {"x1": 22.463044542339695, "x2": 42.511992168379834, "y1": 35.54233969652472, "y2": 44.94028389623103}}, {"id": "00017965", "category": "car", "attributes": {"Crowd": false, "Occluded": true, "Truncated": false}, "box2d": {"x1": 103.786588350465, "x2": 106.41801272638277, "y1": 38.549681840430736, "y2": 42.43416544297602}}, {"id": "00017962", "category": "car", "attributes": {"Crowd": false, "Occluded": true, "Truncated": false}, "box2d": {"x1": 105.03964757709252, "x2": 110.80372001957905, "y1": 38.299069995105235, "y2": 43.43661282427802}}, {"id": "00017932", "category": "car", "attributes": {"Crowd": false, "Occluded": true, "Truncated": true}, "box2d": {"x1": 109.6759667156143, "x2": 160.0, "y1": 30.40479686735199, "y2": 76.76798825256975}}]}