{"name": "03afe274-5430ce20-0000066.jpg", "video_name": "03afe274-5430ce20", "index": 65, "labels": [{"id": "00045900", "category": "car", "attributes": {"Crowd": false, "Occluded": false, "Truncated": true}, "box2d": {"x1": 0.0, "x2": 40.035971223021576, "y1": 37.33812949640287, "y2": 69.38848920863309}}, {"id": "00045901", "category": "car", "attributes": {"Crowd": false, "Occluded": false, "Truncated": false}, "box2d": {"x1": 84.84429440621847, "x2": 104.53929782903901, "y1": 44.564117914348195, "y2": 57.193399770224644}}, {"id": "00045902", "category": "car", "attributes": {"Crowd": false, "Occluded": false, "Truncated": false}, "box2d": {"x1": 72.43755496189931, "x2": 75.24423622917257, "y1": 42.95068543055781, "y2": 44.90813012373224}}, {"id": "00045907", "category": "car", "attributes": {"Crowd": false, "Occluded": false, "Truncated": false}, "box2d": {"x1": 65.98382502673778, "x2": 69.8226816261011, "y1": 41.504159755435396, "y2": 45.064838340352104}}, {"id": "00045912", "category": "car", "attributes": {"Crowd": false, "Occluded": false, "Truncated": false}, "box2d": {"x1": 37.55202747811899, "x2": 47.95836997223677, "y1": 40.113269683202304, "y2": 51.83845137058904}}, {"id": "00045910", "category": "car", "attributes": {"Crowd": false, "Occluded": true, "Truncated": false}, "box2d": {"x1": 82.95268390798147, "x2": 92.2438295904985, "y1": 43.95212628256563, "y2": 53.13200075930403}}, {"id": "00045913", "category": "car", "attributes": {"Crowd": false, "Occluded": true, "Truncated": false}, "box2d": {"x1": 80.78289539529784, "x2": 85.90137086111562, "y1": 43.507041459451045, "y2": 49.79386458594461}}, {"id": "00045905", "category": "car", "attributes": {"Crowd": true, "Occluded": true, "Truncated": false}, "box2d": {"x1": 75.7200555323694, "x2": 82.78577709931349, "y1": 43.061956636336454, "y2": 48.56988132237949}}]}