{"name": "036aaaef-c0fecc6a-0000133.jpg", "video_name": "036aaaef-c0fecc6a", "index": 132, "labels": [{"id": "00084638", "category": "car", "attributes": {"Crowd": false, "Occluded": false, "Truncated": false}, "box2d": {"x1": 201.41263525067535, "x2": 374.2953623368787, "y1": 116.02209944751381, "y2": 271.16022099447514}}, {"id": "00084639", "category": "car", "attributes": {"Crowd": false, "Occluded": true, "Truncated": false}, "box2d": {"x1": 362.91771762172306, "x2": 384.8618784530387, "y1": 152.51194534165438, "y2": 185.6353591160221}}, {"id": "00084734", "category": "car", "attributes": {"Crowd": false, "Occluded": false, "Truncated": true}, "box2d": {"x1": 600.0, "x2": 639.7844567197006, "y1": 165.0828729281768, "y2": 220.11049723756906}}, {"id": "00084735", "category": "car", "attributes": {"Crowd": false, "Occluded": true, "Truncated": false}, "box2d": {"x1": 487.6243093922652, "x2": 619.5580110497237, "y1": 141.21546961325967, "y2": 205.52486187845304}}, {"id": "00084738", "category": "pedestrian", "attributes": {"Crowd": false, "Occluded": true, "Truncated": false}, "box2d": {"x1": 430.6077348066298, "x2": 511.49171270718233, "y1": 146.5193370165746, "y2": 191.6022099447514}}, {"id": "00084744", "category": "car", "attributes": {"Crowd": false, "Occluded": true, "Truncated": true}, "box2d": {"x1": 0.0, "x2": 35.469613259668506, "y1": 150.4972375690608, "y2": 167.73480662983425}}, {"id": "00084751", "category": "car", "attributes": {"Crowd": true, "Occluded": true, "Truncated": false}, "box2d": {"x1": 77.2739708595805, "x2": 107.0718232044199, "y1": 137.90055248618785, "y2": 157.57829351757593}}, {"id": "00084748", "category": "car", "attributes": {"Crowd": false, "Occluded": true, "Truncated": false}, "box2d": {"x1": 374.9171270718232, "x2": 415.9686265980039, "y1": 145.0327674516813, "y2": 177.01657458563537}}, {"id": "00084672", "category": "car", "attributes": {"Crowd": true, "Occluded": true, "Truncated": false}, "box2d": {"x1": 106.90407733297084, "x2": 216.67015358666688, "y1": 137.5443010724995, "y2": 155.22135322991988}}, {"id": "00084750", "category": "car", "attributes": {"Crowd": false, "Occluded": true, "Truncated": false}, "box2d": {"x1": 65.9943280543694, "x2": 78.19991168687395, "y1": 144.95182769084707, "y2": 159.76688092754225}}, {"id": "00084742", "category": "car", "attributes": {"Crowd": false, "Occluded": true, "Truncated": false}, "box2d": {"x1": 399.544076071538, "x2": 458.9296039046368, "y1": 145.7482579171789, "y2": 184.87610569506177}}]}