{"name": "0386df8d-bf0099c3-0000057.jpg", "video_name": "0386df8d-bf0099c3", "index": 56, "labels": [{"id": "00081278", "category": "car", "attributes": {"Crowd": false, "Occluded": false, "Truncated": true}, "box2d": {"x1": 0.0, "x2": 10.157611355849241, "y1": 213.34312285854136, "y2": 252.43857072931962}}, {"id": "00081268", "category": "truck", "attributes": {"Crowd": false, "Occluded": false, "Truncated": false}, "box2d": {"x1": 67.79833578071464, "x2": 147.49290259422418, "y1": 179.76113558492412, "y2": 226.87616250611845}}, {"id": "00081280", "category": "truck", "attributes": {"Crowd": false, "Occluded": true, "Truncated": false}, "box2d": {"x1": 138.97209985315712, "x2": 181.5761135584924, "y1": 183.26970141948115, "y2": 213.84434654919235}}, {"id": "00081275", "category": "pedestrian", "attributes": {"Crowd": false, "Occluded": false, "Truncated": false}, "box2d": {"x1": 185.08467939304944, "x2": 197.61527165932452, "y1": 177.25501713166912, "y2": 213.34312285854136}}, {"id": "00081269", "category": "car", "attributes": {"Crowd": false, "Occluded": true, "Truncated": false}, "box2d": {"x1": 115.41458639255995, "x2": 222.1752325012237, "y1": 158.208516886931, "y2": 208.83210964268233}}, {"id": "00081276", "category": "car", "attributes": {"Crowd": false, "Occluded": true, "Truncated": true}, "box2d": {"x1": 247.73764072442486, "x2": 300.36612824278023, "y1": 172.24278022515907, "y2": 222.3651492902594}}]}