{"name": "0391b282-fbb1dba1-0000199.jpg", "video_name": "0391b282-fbb1dba1", "index": 198, "labels": [{"id": "00015727", "category": "car", "attributes": {"Crowd": false, "Occluded": false, "Truncated": false}, "box2d": {"x1": 408.6301008566002, "x2": 567.3570142050011, "y1": 158.4234718965494, "y2": 225.6547234328364}}, {"id": "00015669", "category": "car", "attributes": {"Crowd": false, "Occluded": false, "Truncated": false}, "box2d": {"x1": 182.448328958239, "x2": 241.80945095196358, "y1": 161.3263721226664, "y2": 223.53466434712175}}, {"id": "00015710", "category": "pedestrian", "attributes": {"Crowd": false, "Occluded": false, "Truncated": false}, "box2d": {"x1": 151.0611188694406, "x2": 159.87369692327502, "y1": 192.2405464799063, "y2": 218.0856283194067}}, {"id": "00015709", "category": "car", "attributes": {"Crowd": false, "Occluded": true, "Truncated": false}, "box2d": {"x1": 239.6675626831169, "x2": 250.59656521336794, "y1": 197.90140835717196, "y2": 209.39482067639125}}, {"id": "00015726", "category": "car", "attributes": {"Crowd": false, "Occluded": false, "Truncated": false}, "box2d": {"x1": 246.4615464145047, "x2": 271.2644266726372, "y1": 193.3539389559276, "y2": 213.5044576399935}}, {"id": "00015713", "category": "car", "attributes": {"Crowd": false, "Occluded": true, "Truncated": false}, "box2d": {"x1": 288.8193044837374, "x2": 302.39589778581524, "y1": 197.52104808413958, "y2": 208.98572687256083}}]}