{"name": "03aa1144-50d56781-0000193.jpg", "video_name": "03aa1144-50d56781", "index": 192, "labels": [{"id": "00035755", "category": "car", "attributes": {"Crowd": false, "Occluded": true, "Truncated": false}, "box2d": {"x1": 114.45086705202311, "x2": 230.98265895953756, "y1": 102.8571428571427, "y2": 179.55408753096614}}, {"id": "00035756", "category": "car", "attributes": {"Crowd": false, "Occluded": true, "Truncated": false}, "box2d": {"x1": 203.0388109000823, "x2": 253.57555739058628, "y1": 101.07349298100738, "y2": 152.20478943022295}}, {"id": "00035769", "category": "car", "attributes": {"Crowd": false, "Occluded": true, "Truncated": false}, "box2d": {"x1": 99.88439306358384, "x2": 145.36746490503717, "y1": 101.07349298100748, "y2": 124.26094137076795}}, {"id": "00035774", "category": "car", "attributes": {"Crowd": false, "Occluded": true, "Truncated": true}, "box2d": {"x1": 0.0, "x2": 146.55656482246079, "y1": 87.39884393063585, "y2": 261.00743187448387}}, {"id": "00035759", "category": "car", "attributes": {"Crowd": false, "Occluded": false, "Truncated": false}, "box2d": {"x1": 233.95540875309678, "x2": 387.943848059455, "y1": 96.31709331131304, "y2": 217.01073492981007}}, {"id": "00035760", "category": "truck", "attributes": {"Crowd": false, "Occluded": true, "Truncated": false}, "box2d": {"x1": 279.735755573906, "x2": 373.0800990916598, "y1": 58.86044591246903, "y2": 121.28819157720892}}, {"id": "00035762", "category": "truck", "attributes": {"Crowd": false, "Occluded": true, "Truncated": true}, "box2d": {"x1": 381.9983484723369, "x2": 639.7357555739059, "y1": 0.0, "y2": 272.89843104872006}}, {"id": "00035763", "category": "truck", "attributes": {"Crowd": false, "Occluded": true, "Truncated": false}, "box2d": {"x1": 367.1345995045417, "x2": 395.0784475639967, "y1": 73.72419488026422, "y2": 105.8298926507019}}, {"id": "00035764", "category": "car", "attributes": {"Crowd": false, "Occluded": true, "Truncated": false}, "box2d": {"x1": 370.10734929810076, "x2": 395.0784475639967, "y1": 99.88439306358379, "y2": 127.8282411230388}}]}