{"name": "03adba3a-eea89633-0000018.jpg", "video_name": "03adba3a-eea89633", "index": 17, "labels": [{"id": "00077147", "category": "car", "attributes": {"Crowd": false, "Occluded": true, "Truncated": false}, "box2d": {"x1": 198.21323688966228, "x2": 206.769713761625, "y1": 265.1295005076599, "y2": 270.1632734516471}}, {"id": "00077148", "category": "car", "attributes": {"Crowd": false, "Occluded": true, "Truncated": false}, "box2d": {"x1": 215.4320213122559, "x2": 223.8254766880581, "y1": 263.1947792840826, "y2": 268.190883674441}}]}