{"name": "03afe274-da9441b2-0000009.jpg", "video_name": "03afe274-da9441b2", "index": 8, "labels": [{"id": "00051168", "category": "car", "attributes": {"Crowd": false, "Occluded": false, "Truncated": false}, "box2d": {"x1": 362.6889860023268, "x2": 460.02456290958355, "y1": 207.11295311163067, "y2": 277.90246358963554}}, {"id": "00051169", "category": "car", "attributes": {"Crowd": false, "Occluded": false, "Truncated": false}, "box2d": {"x1": 182.92652966690335, "x2": 234.9460941848312, "y1": 200.14125889788778, "y2": 236.07229830717813}}, {"id": "00051170", "category": "car", "attributes": {"Crowd": false, "Occluded": false, "Truncated": false}, "box2d": {"x1": 286.80477590658677, "x2": 297.2623172272011, "y1": 206.30852685619882, "y2": 214.6209314956615}}, {"id": "00051171", "category": "car", "attributes": {"Crowd": false, "Occluded": false, "Truncated": false}, "box2d": {"x1": 322.7358153158771, "x2": 342.310187531386, "y1": 202.0182534938955, "y2": 219.17934694310878}}, {"id": "00051172", "category": "car", "attributes": {"Crowd": false, "Occluded": true, "Truncated": false}, "box2d": {"x1": 176.49111962344836, "x2": 204.64603856356393, "y1": 184.58901795953824, "y2": 208.98994770763838}}, {"id": "00051173", "category": "car", "attributes": {"Crowd": false, "Occluded": true, "Truncated": false}, "box2d": {"x1": 49.6599133503563, "x2": 119.6449975729293, "y1": 181.63945502295468, "y2": 212.2076527293659}}]}