{"name": "03b5e695-11d43622-0000041.jpg", "video_name": "03b5e695-11d43622", "index": 40, "labels": [{"id": "00093103", "category": "car", "attributes": {"Crowd": false, "Occluded": true, "Truncated": false}, "box2d": {"x1": 458.45303867403317, "x2": 520.827125323188, "y1": 139.4049360660836, "y2": 191.6022099447514}}, {"id": "00093104", "category": "car", "attributes": {"Crowd": false, "Occluded": true, "Truncated": false}, "box2d": {"x1": 428.17613027854895, "x2": 473.69829547389185, "y1": 138.8693811814325, "y2": 179.03599753026447}}, {"id": "00093097", "category": "car", "attributes": {"Crowd": false, "Occluded": true, "Truncated": false}, "box2d": {"x1": 71.20369542236278, "x2": 132.53965073009397, "y1": 145.1836622473382, "y2": 183.87812601897858}}, {"id": "00093101", "category": "car", "attributes": {"Crowd": false, "Occluded": false, "Truncated": false}, "box2d": {"x1": 286.92516712581033, "x2": 299.39770974785114, "y1": 128.53377286533288, "y2": 139.22160177510247}}, {"id": "00093096", "category": "car", "attributes": {"Crowd": false, "Occluded": false, "Truncated": false}, "box2d": {"x1": 324.9957315708463, "x2": 334.8184269492252, "y1": 122.7836922297361, "y2": 132.606387608115}}, {"id": "00093094", "category": "car", "attributes": {"Crowd": true, "Occluded": true, "Truncated": false}, "box2d": {"x1": 360.3374073400396, "x2": 397.0033179825745, "y1": 124.70211174594118, "y2": 147.43127931940134}}, {"id": "00093102", "category": "car", "attributes": {"Crowd": false, "Occluded": false, "Truncated": true}, "box2d": {"x1": 511.49171270718233, "x2": 640.0, "y1": 139.88950276243094, "y2": 225.52674282969423}}, {"id": "00093095", "category": "car", "attributes": {"Crowd": true, "Occluded": true, "Truncated": false}, "box2d": {"x1": 227.81205811817227, "x2": 279.3655673860495, "y1": 126.22549505396263, "y2": 148.41112564152877}}, {"id": "00093099", "category": "car", "attributes": {"Crowd": false, "Occluded": false, "Truncated": true}, "box2d": {"x1": 0.0, "x2": 77.93848436505357, "y1": 148.9773960548604, "y2": 192.6246389329312}}, {"id": "00093100", "category": "car", "attributes": {"Crowd": false, "Occluded": false, "Truncated": false}, "box2d": {"x1": 214.11892780706353, "x2": 235.26202215301785, "y1": 134.45648381479182, "y2": 149.58743575229386}}]}