{"name": "03c239e4-9e0fbb75-0000004.jpg", "video_name": "03c239e4-9e0fbb75", "index": 3, "labels": [{"id": "00042270", "category": "car", "attributes": {"Crowd": false, "Occluded": false, "Truncated": false}, "box2d": {"x1": 334.5665115461878, "x2": 441.68895624817685, "y1": 172.4508519003932, "y2": 244.65676989140712}}, {"id": "00042271", "category": "car", "attributes": {"Crowd": false, "Occluded": false, "Truncated": false}, "box2d": {"x1": 156.64482306684147, "x2": 319.8951507208388, "y1": 175.28178243774573, "y2": 302.6736566186107}}, {"id": "00042272", "category": "car", "attributes": {"Crowd": false, "Occluded": true, "Truncated": false}, "box2d": {"x1": 151.17307273273568, "x2": 179.71261160422762, "y1": 186.37183717595497, "y2": 210.67369222081695}}, {"id": "00042273", "category": "car", "attributes": {"Crowd": false, "Occluded": true, "Truncated": false}, "box2d": {"x1": 139.1366886409244, "x2": 159.14709499021768, "y1": 186.2567161850218, "y2": 206.11109031742228}}, {"id": "00042274", "category": "car", "attributes": {"Crowd": false, "Occluded": false, "Truncated": false}, "box2d": {"x1": 94.19908717883412, "x2": 119.04631726473887, "y1": 190.9765173213482, "y2": 211.72805014034557}}, {"id": "00042275", "category": "car", "attributes": {"Crowd": false, "Occluded": true, "Truncated": false}, "box2d": {"x1": 56.37276243490594, "x2": 99.5708571907433, "y1": 188.5651443607088, "y2": 206.09575880312457}}, {"id": "00042276", "category": "car", "attributes": {"Crowd": false, "Occluded": true, "Truncated": false}, "box2d": {"x1": 47.2586165166669, "x2": 57.74260994186604, "y1": 190.48609592554135, "y2": 201.29267376382353}}, {"id": "00042277", "category": "car", "attributes": {"Crowd": true, "Occluded": true, "Truncated": false}, "box2d": {"x1": 122.20780660437396, "x2": 144.0905308114623, "y1": 185.24254114767788, "y2": 192.10770870943918}}, {"id": "00042278", "category": "pedestrian", "attributes": {"Crowd": false, "Occluded": false, "Truncated": false}, "box2d": {"x1": 2.9728315654156248, "x2": 15.013029061518166, "y1": 198.56645700210342, "y2": 224.69500162072188}}, {"id": "00042279", "category": "pedestrian", "attributes": {"Crowd": false, "Occluded": true, "Truncated": true}, "box2d": {"x1": 0.0, "x2": 4.50390871845545, "y1": 191.9385207735396, "y2": 223.49598027009003}}, {"id": "00042280", "category": "car", "attributes": {"Crowd": true, "Occluded": true, "Truncated": false}, "box2d": {"x1": 99.61187625501287, "x2": 111.21691757801403, "y1": 185.3712620499507, "y2": 190.531840606254}}, {"id": "00042281", "category": "car", "attributes": {"Crowd": true, "Occluded": true, "Truncated": false}, "box2d": {"x1": 159.2884436842116, "x2": 184.64419573089282, "y1": 184.55364258875406, "y2": 192.7037051914369}}]}