{"name": "03c5f65d-5f77a9a7-0000035.jpg", "video_name": "03c5f65d-5f77a9a7", "index": 34, "labels": [{"id": "00038621", "category": "trailer", "attributes": {"Crowd": false, "Occluded": false, "Truncated": false}, "box2d": {"x1": 263.1548626720933, "x2": 337.1118079388678, "y1": 135.0287469724711, "y2": 211.20044494061673}}, {"id": "00038623", "category": "car", "attributes": {"Crowd": false, "Occluded": true, "Truncated": false}, "box2d": {"x1": 254.81788143587917, "x2": 268.4472738755774, "y1": 156.5942413390824, "y2": 201.10542171176812}}, {"id": "00038624", "category": "pedestrian", "attributes": {"Crowd": false, "Occluded": false, "Truncated": false}, "box2d": {"x1": 229.7636752725927, "x2": 236.35781825805984, "y1": 162.91141598816765, "y2": 179.47371566172512}}, {"id": "00038634", "category": "pedestrian", "attributes": {"Crowd": false, "Occluded": false, "Truncated": false}, "box2d": {"x1": 236.7888794635359, "x2": 243.4973846937478, "y1": 162.4424098488441, "y2": 179.2333701341038}}, {"id": "00038631", "category": "pedestrian", "attributes": {"Crowd": false, "Occluded": false, "Truncated": false}, "box2d": {"x1": 386.36518183356844, "x2": 401.051017797831, "y1": 151.4528488449459, "y2": 190.2142314044523}}, {"id": "00038640", "category": "pedestrian", "attributes": {"Crowd": false, "Occluded": true, "Truncated": false}, "box2d": {"x1": 375.57189697762095, "x2": 385.680170815653, "y1": 157.90980953289014, "y2": 186.75579083346227}}, {"id": "00038629", "category": "pedestrian", "attributes": {"Crowd": false, "Occluded": false, "Truncated": false}, "box2d": {"x1": 47.27156365161196, "x2": 58.31309676731695, "y1": 166.0830588603914, "y2": 185.4057418128751}}, {"id": "00038635", "category": "car", "attributes": {"Crowd": false, "Occluded": true, "Truncated": false}, "box2d": {"x1": 97.25182385466847, "x2": 112.9570254295525, "y1": 169.11166020858616, "y2": 181.98487546308323}}, {"id": "00038630", "category": "pedestrian", "attributes": {"Crowd": true, "Occluded": false, "Truncated": false}, "box2d": {"x1": 142.1597388647017, "x2": 161.8274697270512, "y1": 161.942483942002, "y2": 184.79600784323458}}, {"id": "00038633", "category": "pedestrian", "attributes": {"Crowd": false, "Occluded": false, "Truncated": false}, "box2d": {"x1": 123.87874337059222, "x2": 131.7418644465702, "y1": 167.08319414153152, "y2": 177.71585624471751}}, {"id": "00038638", "category": "car", "attributes": {"Crowd": true, "Occluded": true, "Truncated": false}, "box2d": {"x1": 245.19681118077386, "x2": 253.58348843289295, "y1": 161.36397426681782, "y2": 175.3090090799996}}, {"id": "00038639", "category": "car", "attributes": {"Crowd": false, "Occluded": true, "Truncated": false}, "box2d": {"x1": 251.65163864837803, "x2": 266.5412522213582, "y1": 155.95671586986978, "y2": 176.73197181603862}}, {"id": "00038641", "category": "car", "attributes": {"Crowd": false, "Occluded": true, "Truncated": false}, "box2d": {"x1": 184.6512796373499, "x2": 192.47374187393774, "y1": 169.0063551641742, "y2": 175.18198324569093}}]}