{"name": "0373ecad-17c44420-0000114.jpg", "video_name": "0373ecad-17c44420", "index": 113, "labels": [{"id": "00008523", "category": "car", "attributes": {"Crowd": false, "Occluded": true, "Truncated": false}, "box2d": {"x1": 96.77154582763339, "x2": 243.52941176470588, "y1": 93.93980848153215, "y2": 171.75102599179206}}, {"id": "00008552", "category": "car", "attributes": {"Crowd": false, "Occluded": true, "Truncated": false}, "box2d": {"x1": 140.50740864575405, "x2": 175.22769940510463, "y1": 88.02041110464025, "y2": 95.58244102437048}}, {"id": "00008544", "category": "truck", "attributes": {"Crowd": false, "Occluded": false, "Truncated": false}, "box2d": {"x1": 105.30472499491853, "x2": 113.38566312402499, "y1": 94.36178794508686, "y2": 100.75919729729617}}, {"id": "00008546", "category": "car", "attributes": {"Crowd": false, "Occluded": true, "Truncated": false}, "box2d": {"x1": 91.41561258551681, "x2": 100.00160934769241, "y1": 96.5503753550532, "y2": 103.62119621802134}}, {"id": "00008549", "category": "car", "attributes": {"Crowd": false, "Occluded": false, "Truncated": true}, "box2d": {"x1": 82.24038075142718, "x2": 94.36178794508686, "y1": 97.39213974350179, "y2": 105.80978362798768}}, {"id": "00008559", "category": "car", "attributes": {"Crowd": false, "Occluded": false, "Truncated": true}, "box2d": {"x1": 0.0, "x2": 7.2391737406578684, "y1": 103.87372553455592, "y2": 118.60460233240623}}, {"id": "00008545", "category": "truck", "attributes": {"Crowd": false, "Occluded": true, "Truncated": false}, "box2d": {"x1": 112.88060449095583, "x2": 119.27801384316511, "y1": 93.35167067894855, "y2": 99.24402139808868}}, {"id": "00008547", "category": "car", "attributes": {"Crowd": true, "Occluded": true, "Truncated": false}, "box2d": {"x1": 129.21083362685846, "x2": 138.13353614441354, "y1": 94.277611506242, "y2": 96.9712575492775}}, {"id": "00008563", "category": "pedestrian", "attributes": {"Crowd": false, "Occluded": true, "Truncated": false}, "box2d": {"x1": 80.58194327795546, "x2": 83.08439762075744, "y1": 96.9096239903815, "y2": 104.57680771472705}}, {"id": "00008566", "category": "pedestrian", "attributes": {"Crowd": false, "Occluded": false, "Truncated": false}, "box2d": {"x1": 32.30290749360164, "x2": 36.69751846273012, "y1": 98.92051155934521, "y2": 110.08076224417623}}, {"id": "00008536", "category": "pedestrian", "attributes": {"Crowd": false, "Occluded": false, "Truncated": false}, "box2d": {"x1": 7.559424107485635, "x2": 16.345477820240575, "y1": 100.03186030896141, "y2": 116.95068203813152}}, {"id": "00008567", "category": "pedestrian", "attributes": {"Crowd": false, "Occluded": true, "Truncated": false}, "box2d": {"x1": 39.217334954557124, "x2": 42.77544656574244, "y1": 99.6783121594245, "y2": 108.14826500166579}}, {"id": "00008565", "category": "pedestrian", "attributes": {"Crowd": false, "Occluded": true, "Truncated": false}, "box2d": {"x1": 47.490584529411386, "x2": 50.96877592402712, "y1": 98.92684385238812, "y2": 107.17074931710172}}, {"id": "00008568", "category": "car", "attributes": {"Crowd": false, "Occluded": true, "Truncated": false}, "box2d": {"x1": 119.51752504727021, "x2": 122.17884645520539, "y1": 95.08175575622914, "y2": 97.58178495762279}}]}