{"name": "0378d8dc-92df7b3e-0000035.jpg", "video_name": "0378d8dc-92df7b3e", "index": 34, "labels": [{"id": "00062843", "category": "car", "attributes": {"Crowd": false, "Occluded": false, "Truncated": true}, "box2d": {"x1": 250.50820855478133, "x2": 319.9525498405551, "y1": 160.72294550444428, "y2": 180.0}}, {"id": "00062844", "category": "car", "attributes": {"Crowd": false, "Occluded": true, "Truncated": false}, "box2d": {"x1": 186.3471405074699, "x2": 201.99973060389843, "y1": 151.05766465370374, "y2": 167.42173611815176}}, {"id": "00062861", "category": "car", "attributes": {"Crowd": false, "Occluded": false, "Truncated": false}, "box2d": {"x1": 170.51159929998997, "x2": 176.3457465177497, "y1": 160.28659067669557, "y2": 164.27088633760465}}, {"id": "00062848", "category": "car", "attributes": {"Crowd": false, "Occluded": false, "Truncated": false}, "box2d": {"x1": 145.03600412969195, "x2": 154.63211815800585, "y1": 158.33588146717966, "y2": 167.09023110704499}}, {"id": "00062862", "category": "car", "attributes": {"Crowd": false, "Occluded": false, "Truncated": false}, "box2d": {"x1": 195.70623818393662, "x2": 223.40619804997073, "y1": 158.27115362104044, "y2": 178.59449374014156}}, {"id": "00062868", "category": "car", "attributes": {"Crowd": false, "Occluded": true, "Truncated": false}, "box2d": {"x1": 184.09387175370648, "x2": 187.96598794057, "y1": 161.45040970443944, "y2": 164.8174672582338}}, {"id": "00062853", "category": "pedestrian", "attributes": {"Crowd": false, "Occluded": false, "Truncated": false}, "box2d": {"x1": 97.965179745943, "x2": 102.74349322400164, "y1": 155.10991006504253, "y2": 169.15230545599204}}, {"id": "00062857", "category": "pedestrian", "attributes": {"Crowd": false, "Occluded": false, "Truncated": false}, "box2d": {"x1": 93.71345651168086, "x2": 97.14604029256155, "y1": 155.10991006504253, "y2": 167.63104289997614}}, {"id": "00062855", "category": "pedestrian", "attributes": {"Crowd": false, "Occluded": false, "Truncated": false}, "box2d": {"x1": 89.24719496833181, "x2": 93.83047494560729, "y1": 156.22160289436772, "y2": 171.0051185054833}}, {"id": "00062856", "category": "car", "attributes": {"Crowd": false, "Occluded": true, "Truncated": false}, "box2d": {"x1": 154.11470335042736, "x2": 158.14700851396552, "y1": 159.84057668265152, "y2": 165.64709611814644}}, {"id": "00062864", "category": "car", "attributes": {"Crowd": false, "Occluded": false, "Truncated": false}, "box2d": {"x1": 223.52429850879497, "x2": 245.53787420064495, "y1": 160.45998683824124, "y2": 176.17960419192903}}, {"id": "00062867", "category": "pedestrian", "attributes": {"Crowd": false, "Occluded": true, "Truncated": false}, "box2d": {"x1": 256.5193058955243, "x2": 263.85398779680173, "y1": 155.3681756946058, "y2": 171.94814492135282}}, {"id": "00062866", "category": "car", "attributes": {"Crowd": false, "Occluded": true, "Truncated": false}, "box2d": {"x1": 218.2709744581871, "x2": 234.35340665940146, "y1": 157.1611233872956, "y2": 170.77216983951442}}, {"id": "00062863", "category": "bus", "attributes": {"Crowd": false, "Occluded": true, "Truncated": false}, "box2d": {"x1": 178.41637903616558, "x2": 184.57943182800986, "y1": 159.51765926665942, "y2": 164.54952067041273}}, {"id": "00062854", "category": "car", "attributes": {"Crowd": false, "Occluded": true, "Truncated": false}, "box2d": {"x1": 153.29610246580035, "x2": 161.89706672630584, "y1": 156.41663014561277, "y2": 165.15411764834852}}, {"id": "00062859", "category": "car", "attributes": {"Crowd": false, "Occluded": true, "Truncated": false}, "box2d": {"x1": 162.09866757423288, "x2": 166.6148493573956, "y1": 160.64703771535915, "y2": 164.8406350854388}}, {"id": "00062869", "category": "pedestrian", "attributes": {"Crowd": false, "Occluded": true, "Truncated": false}, "box2d": {"x1": 250.81270286844492, "x2": 253.43144916587244, "y1": 157.51781760477476, "y2": 167.94529146601982}}]}