{"name": "0386df8d-c884dc14-0000171.jpg", "video_name": "0386df8d-c884dc14", "index": 170, "labels": [{"id": "00014521", "category": "car", "attributes": {"Crowd": false, "Occluded": true, "Truncated": false}, "box2d": {"x1": 90.6491554709007, "x2": 116.93623176480298, "y1": 99.72585894457995, "y2": 117.99714515783043}}, {"id": "00014530", "category": "car", "attributes": {"Crowd": false, "Occluded": false, "Truncated": false}, "box2d": {"x1": 159.3041050605923, "x2": 192.0253241379678, "y1": 97.65073065594177, "y2": 116.93623176480298}}, {"id": "00014531", "category": "car", "attributes": {"Crowd": false, "Occluded": true, "Truncated": true}, "box2d": {"x1": 256.858920378534, "x2": 320.0, "y1": 82.397606858465, "y2": 137.09358623232447}}, {"id": "00014534", "category": "car", "attributes": {"Crowd": false, "Occluded": true, "Truncated": false}, "box2d": {"x1": 87.68331314105951, "x2": 91.5921895980362, "y1": 106.48122497468226, "y2": 113.2819745221529}}, {"id": "00014535", "category": "pedestrian", "attributes": {"Crowd": false, "Occluded": false, "Truncated": false}, "box2d": {"x1": 194.02927165813074, "x2": 206.87811164035205, "y1": 104.32315031436556, "y2": 118.35078295550625}}]}