{"name": "038cd048-0a261ef9-0000068.jpg", "video_name": "038cd048-0a261ef9", "index": 67, "labels": [{"id": "00084403", "category": "truck", "attributes": {"Crowd": false, "Occluded": false, "Truncated": false}, "box2d": {"x1": 153.83586811172793, "x2": 182.4032194899438, "y1": 56.69444488546416, "y2": 79.607033147767}}, {"id": "00084423", "category": "car", "attributes": {"Crowd": false, "Occluded": true, "Truncated": true}, "box2d": {"x1": 216.09436435124508, "x2": 320.0, "y1": 40.9305373525557, "y2": 136.23853211009174}}, {"id": "00084443", "category": "car", "attributes": {"Crowd": false, "Occluded": true, "Truncated": false}, "box2d": {"x1": 23.801421479068843, "x2": 99.79894269293777, "y1": 48.4658180489801, "y2": 81.31456348208096}}, {"id": "00084444", "category": "car", "attributes": {"Crowd": false, "Occluded": true, "Truncated": true}, "box2d": {"x1": 0.0, "x2": 11.83111593988802, "y1": 68.23074114855774, "y2": 74.63346271602654}}, {"id": "00084407", "category": "car", "attributes": {"Crowd": false, "Occluded": false, "Truncated": false}, "box2d": {"x1": 186.42771297212585, "x2": 193.071082438472, "y1": 64.27829169931074, "y2": 70.33113943531502}}, {"id": "00084434", "category": "car", "attributes": {"Crowd": false, "Occluded": true, "Truncated": false}, "box2d": {"x1": 180.37486523612156, "x2": 183.91799561817285, "y1": 63.83540040155433, "y2": 68.55957424428938}}, {"id": "00084433", "category": "car", "attributes": {"Crowd": false, "Occluded": true, "Truncated": false}, "box2d": {"x1": 192.33293027554464, "x2": 196.90947368569422, "y1": 65.01644386223809, "y2": 69.4453568398022}}, {"id": "00084442", "category": "car", "attributes": {"Crowd": true, "Occluded": true, "Truncated": false}, "box2d": {"x1": 185.80768361767423, "x2": 202.27691267059205, "y1": 56.95251813421699, "y2": 63.360296023939526}}, {"id": "00084446", "category": "car", "attributes": {"Crowd": true, "Occluded": true, "Truncated": false}, "box2d": {"x1": 206.71020291081075, "x2": 217.00856457377247, "y1": 57.38879482638904, "y2": 62.47731460880687}}, {"id": "00084445", "category": "car", "attributes": {"Crowd": false, "Occluded": true, "Truncated": false}, "box2d": {"x1": 162.40486944555474, "x2": 168.03118583939838, "y1": 49.43602143743877, "y2": 52.08887167668266}}]}