{"name": "03bf498b-044cb72c-0000169.jpg", "video_name": "03bf498b-044cb72c", "index": 168, "labels": [{"id": "00011051", "category": "car", "attributes": {"Crowd": false, "Occluded": false, "Truncated": false}, "box2d": {"x1": 89.43219583523931, "x2": 124.76827528620635, "y1": 98.4251818332119, "y2": 126.31423287457969}}, {"id": "00011052", "category": "car", "attributes": {"Crowd": false, "Occluded": false, "Truncated": false}, "box2d": {"x1": 32.69686702828051, "x2": 50.622053013327694, "y1": 93.22203289605288, "y2": 105.40258707054127}}, {"id": "00011055", "category": "car", "attributes": {"Crowd": false, "Occluded": true, "Truncated": false}, "box2d": {"x1": 17.161931656129827, "x2": 23.624228057865544, "y1": 93.32060212069707, "y2": 96.54841236881397}}, {"id": "00011081", "category": "car", "attributes": {"Crowd": false, "Occluded": true, "Truncated": false}, "box2d": {"x1": 1.1712924265771, "x2": 9.634768649055342, "y1": 93.93580646575833, "y2": 98.50547475065333}}, {"id": "00011057", "category": "car", "attributes": {"Crowd": false, "Occluded": true, "Truncated": false}, "box2d": {"x1": 48.46439173734979, "x2": 52.44776640069361, "y1": 94.05190261758285, "y2": 103.8443653316364}}]}