{"name": "03c28a8d-9fd776c9-0000173.jpg", "video_name": "03c28a8d-9fd776c9", "index": 172, "labels": [{"id": "00109739", "category": "car", "attributes": {"Crowd": false, "Occluded": true, "Truncated": false}, "box2d": {"x1": 173.1651088499926, "x2": 182.51207630307294, "y1": 53.13972259888251, "y2": 59.77767737172319}}, {"id": "00109768", "category": "car", "attributes": {"Crowd": false, "Occluded": true, "Truncated": false}, "box2d": {"x1": 13.652322139845234, "x2": 42.731772734887606, "y1": 57.74933354657337, "y2": 73.33248796912525}}, {"id": "00109753", "category": "car", "attributes": {"Crowd": false, "Occluded": true, "Truncated": false}, "box2d": {"x1": 38.519057554848686, "x2": 62.93721362655368, "y1": 54.453270924743606, "y2": 68.92473460114967}}, {"id": "00109772", "category": "car", "attributes": {"Crowd": false, "Occluded": true, "Truncated": true}, "box2d": {"x1": 0.0, "x2": 18.751765992609922, "y1": 57.13244374586724, "y2": 77.21177110420372}}, {"id": "00109779", "category": "car", "attributes": {"Crowd": false, "Occluded": false, "Truncated": false}, "box2d": {"x1": 58.11989469824606, "x2": 86.2758630055231, "y1": 54.42991471008746, "y2": 74.9512606093588}}, {"id": "00109766", "category": "pedestrian", "attributes": {"Crowd": false, "Occluded": true, "Truncated": false}, "box2d": {"x1": 108.84202939627666, "x2": 117.58333168812102, "y1": 53.54821024786569, "y2": 80.90786772451307}}, {"id": "00109755", "category": "pedestrian", "attributes": {"Crowd": false, "Occluded": true, "Truncated": false}, "box2d": {"x1": 109.42937049831662, "x2": 124.6386640863417, "y1": 53.139538950911586, "y2": 81.65114567951316}}, {"id": "00109790", "category": "pedestrian", "attributes": {"Crowd": false, "Occluded": false, "Truncated": false}, "box2d": {"x1": 140.3520272342794, "x2": 151.9210055039101, "y1": 54.562031277313196, "y2": 78.51262715718262}}, {"id": "00109801", "category": "pedestrian", "attributes": {"Crowd": false, "Occluded": true, "Truncated": false}, "box2d": {"x1": 225.26558763609592, "x2": 246.49545138067992, "y1": 55.101933195363245, "y2": 146.66396025354857}}, {"id": "00109803", "category": "pedestrian", "attributes": {"Crowd": false, "Occluded": true, "Truncated": false}, "box2d": {"x1": 228.7390247380469, "x2": 267.1682626538988, "y1": 61.13066128810253, "y2": 153.52941176470588}}, {"id": "00109806", "category": "pedestrian", "attributes": {"Crowd": false, "Occluded": true, "Truncated": false}, "box2d": {"x1": 250.77626149406552, "x2": 279.1652216329848, "y1": 57.53083095015543, "y2": 144.79296367604715}}, {"id": "00109797", "category": "car", "attributes": {"Crowd": false, "Occluded": true, "Truncated": false}, "box2d": {"x1": 139.49046628255738, "x2": 156.52964335543552, "y1": 60.23010112687247, "y2": 73.05432908832955}}, {"id": "00109804", "category": "truck", "attributes": {"Crowd": false, "Occluded": true, "Truncated": true}, "box2d": {"x1": 171.62790697674419, "x2": 320.0, "y1": 6.279069767441861, "y2": 103.296853625171}}, {"id": "00109805", "category": "pedestrian", "attributes": {"Crowd": false, "Occluded": false, "Truncated": false}, "box2d": {"x1": 13.026794216901877, "x2": 24.3657674076958, "y1": 58.87913996605251, "y2": 82.68568291593066}}, {"id": "00109764", "category": "car", "attributes": {"Crowd": false, "Occluded": true, "Truncated": false}, "box2d": {"x1": 83.64673057819373, "x2": 99.19552042749652, "y1": 53.452179215027385, "y2": 67.04901442953319}}, {"id": "00109798", "category": "pedestrian", "attributes": {"Crowd": false, "Occluded": false, "Truncated": false}, "box2d": {"x1": 65.20237449441159, "x2": 78.24284939329391, "y1": 55.972427975072804, "y2": 79.51705782497196}}]}