{"name": "03c66a02-3deee2e5-0000076.jpg", "video_name": "03c66a02-3deee2e5", "index": 75, "labels": [{"id": "00079650", "category": "car", "attributes": {"Crowd": false, "Occluded": false, "Truncated": false}, "box2d": {"x1": 183.9070601385043, "x2": 197.87413881494297, "y1": 92.88322782867016, "y2": 103.90986784720114}}, {"id": "00079762", "category": "car", "attributes": {"Crowd": false, "Occluded": true, "Truncated": false}, "box2d": {"x1": 196.6589257034327, "x2": 198.89127024705928, "y1": 94.71518992244293, "y2": 99.17987900969612}}, {"id": "00079761", "category": "bus", "attributes": {"Crowd": false, "Occluded": true, "Truncated": false}, "box2d": {"x1": 185.69459439426998, "x2": 191.64052221214578, "y1": 91.28163979669415, "y2": 94.69296391658969}}, {"id": "00079753", "category": "pedestrian", "attributes": {"Crowd": false, "Occluded": false, "Truncated": false}, "box2d": {"x1": 116.2443722669782, "x2": 118.33527742991241, "y1": 92.39809595864088, "y2": 97.6253588659764}}, {"id": "00079677", "category": "car", "attributes": {"Crowd": false, "Occluded": false, "Truncated": false}, "box2d": {"x1": 123.95306072716217, "x2": 131.2112100215308, "y1": 91.4526811090448, "y2": 97.82372326743506}}, {"id": "00079679", "category": "bus", "attributes": {"Crowd": false, "Occluded": false, "Truncated": false}, "box2d": {"x1": 208.11778578657618, "x2": 247.94760770534535, "y1": 82.64780391418306, "y2": 108.59764785996133}}, {"id": "00079721", "category": "bus", "attributes": {"Crowd": false, "Occluded": true, "Truncated": false}, "box2d": {"x1": 86.22430799757748, "x2": 91.41450906150932, "y1": 88.12180256280381, "y2": 91.97259690055971}}, {"id": "00079700", "category": "car", "attributes": {"Crowd": false, "Occluded": false, "Truncated": false}, "box2d": {"x1": 168.62294140948765, "x2": 174.87187316394446, "y1": 93.00756591928624, "y2": 98.67113448089655}}, {"id": "00079733", "category": "car", "attributes": {"Crowd": false, "Occluded": false, "Truncated": true}, "box2d": {"x1": 0.0, "x2": 75.85102342026268, "y1": 71.2440492287916, "y2": 135.75593966851932}}, {"id": "00079737", "category": "car", "attributes": {"Crowd": false, "Occluded": false, "Truncated": false}, "box2d": {"x1": 84.97935012131097, "x2": 113.34492379008695, "y1": 85.54195281534537, "y2": 106.58113538175836}}, {"id": "00079741", "category": "car", "attributes": {"Crowd": false, "Occluded": true, "Truncated": false}, "box2d": {"x1": 258.42178523157446, "x2": 278.81446520874255, "y1": 97.76957635147032, "y2": 106.4831867826146}}, {"id": "00079731", "category": "bus", "attributes": {"Crowd": false, "Occluded": true, "Truncated": false}, "box2d": {"x1": 248.45303867403317, "x2": 278.100160375037, "y1": 88.37180372742598, "y2": 101.27672915104169}}, {"id": "00079751", "category": "bus", "attributes": {"Crowd": false, "Occluded": true, "Truncated": false}, "box2d": {"x1": 280.2241686528075, "x2": 314.13751649424904, "y1": 91.1597811006589, "y2": 104.11820308515001}}, {"id": "00079755", "category": "truck", "attributes": {"Crowd": false, "Occluded": true, "Truncated": false}, "box2d": {"x1": 281.1259849340628, "x2": 311.74514590514576, "y1": 95.92892668774954, "y2": 105.95135186408157}}, {"id": "00079734", "category": "car", "attributes": {"Crowd": false, "Occluded": false, "Truncated": false}, "box2d": {"x1": 177.01819667932398, "x2": 182.01825508211124, "y1": 93.54947979408465, "y2": 97.90436937070582}}, {"id": "00079735", "category": "car", "attributes": {"Crowd": false, "Occluded": false, "Truncated": false}, "box2d": {"x1": 155.08245658967647, "x2": 165.3245117050634, "y1": 93.71077200062616, "y2": 99.35599922957957}}, {"id": "00079745", "category": "car", "attributes": {"Crowd": false, "Occluded": false, "Truncated": false}, "box2d": {"x1": 141.1306807238346, "x2": 150.24369039343077, "y1": 92.25914214175245, "y2": 99.75922974593337}}, {"id": "00079763", "category": "truck", "attributes": {"Crowd": false, "Occluded": true, "Truncated": false}, "box2d": {"x1": 147.5823689854956, "x2": 151.45338194249223, "y1": 91.2913889025033, "y2": 96.29144730529057}}, {"id": "00079754", "category": "car", "attributes": {"Crowd": false, "Occluded": true, "Truncated": false}, "box2d": {"x1": 75.00087604180925, "x2": 86.1300382931745, "y1": 92.50108045156473, "y2": 98.79147650668422}}, {"id": "00079757", "category": "truck", "attributes": {"Crowd": false, "Occluded": false, "Truncated": false}, "box2d": {"x1": 153.14695011117823, "x2": 157.17925527471635, "y1": 90.72686617960795, "y2": 94.7591713431461}}, {"id": "00079758", "category": "car", "attributes": {"Crowd": false, "Occluded": true, "Truncated": false}, "box2d": {"x1": 131.40520177237636, "x2": 135.83338754611617, "y1": 92.22240732189425, "y2": 96.54898016545908}}, {"id": "00079759", "category": "car", "attributes": {"Crowd": false, "Occluded": true, "Truncated": false}, "box2d": {"x1": 134.92445195918066, "x2": 139.08026552607225, "y1": 92.80176031371391, "y2": 96.43611163129589}}, {"id": "00079685", "category": "train", "attributes": {"Crowd": false, "Occluded": true, "Truncated": false}, "box2d": {"x1": 71.21466624745902, "x2": 143.054023055806, "y1": 78.18489367625277, "y2": 83.44544154322554}}, {"id": "00079746", "category": "car", "attributes": {"Crowd": true, "Occluded": true, "Truncated": false}, "box2d": {"x1": 139.31695956218235, "x2": 142.9310142524882, "y1": 92.09187630192831, "y2": 95.5985359859882}}]}